jsrify/__init__.py
jsrify/asr_utils.py
jsrify/audio_utils.py
jsrify/confusion_matrices.py
jsrify/data_utils.py
jsrify/metrics.py
jsrify/noise_utils.py
jsrify/pipeline.py
jsrify/usage.py
jsrify/visualization.py
jsrify/__pycache__/__init__.cpython-311.pyc
jsrify/__pycache__/asr_utils.cpython-311.pyc
jsrify/__pycache__/audio_utils.cpython-311.pyc
jsrify/__pycache__/confusion_matrices.cpython-311.pyc
jsrify/__pycache__/data_utils.cpython-311.pyc
jsrify/__pycache__/metrics.cpython-311.pyc
jsrify/__pycache__/noise_utils.cpython-311.pyc
jsrify/__pycache__/pipeline.cpython-311.pyc
jsrify/__pycache__/usage.cpython-311.pyc
jsrify/__pycache__/visualization.cpython-311.pyc
jsrify-0.1.2.dist-info/licenses/LICENSE
jsrify-0.1.2.dist-info/METADATA
jsrify-0.1.2.dist-info/WHEEL
jsrify-0.1.2.dist-info/entry_points.txt
jsrify-0.1.2.dist-info/top_level.txt
jsrify-0.1.2.dist-info/RECORD
