Metadata-Version: 2.4
Name: jsrify
Version: 0.1.2
Summary: A plug-and-play tool to detect and rate hallucinations in ASR outputs.
Home-page: https://github.com/yourusername/jsrify
Author: Anshit Mukherjee
Author-email: anshitmukherjee1@gmail.com
License: MIT
Requires-Python: >=3.8
License-File: LICENSE
Requires-Dist: openai-whisper
Requires-Dist: soundfile
Requires-Dist: numpy
Requires-Dist: scipy
Requires-Dist: jiwer
Requires-Dist: librosa
Requires-Dist: torch
Requires-Dist: torchaudio
Requires-Dist: matplotlib
Requires-Dist: seaborn
Dynamic: author
Dynamic: author-email
Dynamic: description
Dynamic: description-content-type
Dynamic: home-page
Dynamic: license
Dynamic: license-file
Dynamic: requires-dist
Dynamic: requires-python
Dynamic: summary
